livingpark_utils/__init__.py
livingpark_utils/cli.py
livingpark_utils/clinical.py
livingpark_utils/deprecation.py
livingpark_utils/ignore.py
livingpark_utils/livingpark_utils.py
livingpark_utils/toggle_button.html
livingpark_utils/visualization.py
livingpark_utils/dataset/__init__.py
livingpark_utils/dataset/convert.py
livingpark_utils/dataset/ppmi.py
livingpark_utils/download/DownloaderABC.py
livingpark_utils/download/__init__.py
livingpark_utils/download/ppmi.py
livingpark_utils/maketal/maketal.py
livingpark_utils/notebooks/mri_metadata.ipynb
livingpark_utils/notebooks/pd_status.ipynb
livingpark_utils/pipeline/PipelineABC.py
livingpark_utils/pipeline/__init__.py
livingpark_utils/pipeline/exceptions.py
livingpark_utils/pipeline/qc.py
livingpark_utils/pipeline/spm.py
livingpark_utils/scripts/__init__.py
livingpark_utils/scripts/_gen_run.py
livingpark_utils/scripts/mri_metadata.py
livingpark_utils/scripts/pd_status.py
livingpark_utils/scripts/run.py
livingpark_utils/templates/call_batch.m
livingpark_utils/templates/dartel_normalization_job.m
livingpark_utils/templates/pairwise_registration_job.m
livingpark_utils/templates/segmentation_job.m
livingpark_utils/templates/spatial_normalization_job.m
livingpark_utils/templates/spatial_smoothing_job.m
livingpark_utils/templates/stats_job.m
livingpark_utils/templates/tissue_volumes_job.m
livingpark_utils/zeighamietal/__init__.py
livingpark_utils/zeighamietal/constants.py
livingpark_utils/zeighamietal/zeighamietal.py
livingpark_utils-0.9.5.dist-info/METADATA
livingpark_utils-0.9.5.dist-info/WHEEL
livingpark_utils-0.9.5.dist-info/entry_points.txt
livingpark_utils-0.9.5.dist-info/licenses/LICENSE
livingpark_utils-0.9.5.dist-info/RECORD
