Metadata-Version: 2.3
Name: livingpark_utils
Version: 0.9.5
Summary: Utility functions to write LivingPark notebooks.
Project-URL: Bug Tracker, https://github.com/LivingPark-MRI/livingpark_utils/issues
Author-email: Tristan Glatard <tristan.glatard@concordia.ca>
License: MIT License
Classifier: License :: OSI Approved :: MIT License
Classifier: Programming Language :: Python :: 3
Requires-Python: >=3.10
Requires-Dist: boutiques
Requires-Dist: click
Requires-Dist: datalad
Requires-Dist: dcm2niix
Requires-Dist: ipython
Requires-Dist: matplotlib
Requires-Dist: nilearn
Requires-Dist: nipype
Requires-Dist: numpy
Requires-Dist: pandas
Requires-Dist: pillow
Requires-Dist: ppmi-downloader>=0.7.6
Requires-Dist: pytz
